vitosa-1.0.0.post79.dist-info/licenses/LICENSE
vitosa_pipeline/__init__.py
vitosa_pipeline/vitosa_pipeline.py
vitosa-1.0.0.post79.dist-info/METADATA
vitosa-1.0.0.post79.dist-info/WHEEL
vitosa-1.0.0.post79.dist-info/top_level.txt
vitosa-1.0.0.post79.dist-info/RECORD
