Metadata-Version: 2.4
Name: vitosa
Version: 1.0.0.post79
Summary: Vietnamese Audio-based Toxic Spans Detection Pipeline
Home-page: https://github.com/vitosa-research/ViToSA-Dataset
Author: Luan Thanh Nguyen
Author-email: luannt@uit.edu.vn
License: MIT
Project-URL: Documentation, https://github.com/vitosa-research/ViToSA-Dataset#readme
Project-URL: Source, https://github.com/vitosa-research/ViToSA-Dataset
Project-URL: Tracker, https://github.com/vitosa-research/ViToSA-Dataset/issues
Keywords: toxic detection,vietnamese,NLP,transformers,audio
Classifier: Programming Language :: Python :: 3
Classifier: License :: OSI Approved :: MIT License
Classifier: Operating System :: OS Independent
Classifier: Topic :: Scientific/Engineering :: Artificial Intelligence
Classifier: Intended Audience :: Developers
License-File: LICENSE
Dynamic: license-file
